COPYING.txt
MANIFEST.in
README.rst
setup.py
user_behavior/__init__.py
user_behavior/__init__.pyc
user_behavior/base.py
user_behavior/base.pyc
user_behavior/decorators.py
user_behavior/decorators.pyc
user_behavior/filters.py
user_behavior/filters.pyc
user_behavior/middleware.py
user_behavior/middleware.pyc
user_behavior/serializers.py
user_behavior/serializers.pyc
user_behavior/services.py
user_behavior/services.pyc
user_behavior/tasks.py
user_behavior/tasks.pyc
user_behavior/urls.py
user_behavior/urls.pyc
user_behavior/views.py
user_behavior/views.pyc
user_behavior.egg-info/PKG-INFO
user_behavior.egg-info/SOURCES.txt
user_behavior.egg-info/dependency_links.txt
user_behavior.egg-info/pbr.json
user_behavior.egg-info/top_level.txt
user_behavior.egg-info/zip-safe
user_behavior/migrations/0001_initial.py
user_behavior/migrations/0001_initial.pyc
user_behavior/migrations/__init__.py
user_behavior/migrations/__init__.pyc
user_behavior/models/__init__.py
user_behavior/models/__init__.pyc
user_behavior/models/api_info.py
user_behavior/models/api_info.pyc
user_behavior/models/user_behavior.py
user_behavior/models/user_behavior.pyc