Metadata-Version: 1.1
Name: user-behavior
Version: 1.2.6
Summary: this is a package for you to extract user behaviors.
Home-page: https://github.com/mkloveyy/user_behaviors
Author: ma_k
Author-email: ma_k@ctrip.com
License: MIT
Keywords: test user behavior
Platform: UNKNOWN
Classifier: License :: OSI Approved :: MIT License
Classifier: Framework :: Django
Classifier: Programming Language :: Python :: 2.7
Classifier: Intended Audience :: Developers
Classifier: Operating System :: OS Independent
